bipartitepandas/__init__.py
bipartitepandas/bipartitebase.py
bipartitepandas/bipartitedataframe.py
bipartitepandas/bipartiteeventstudy.py
bipartitepandas/bipartiteeventstudybase.py
bipartitepandas/bipartiteeventstudycollapsed.py
bipartitepandas/bipartiteextendedeventstudy.py
bipartitepandas/bipartiteextendedeventstudybase.py
bipartitepandas/bipartiteextendedeventstudycollapsed.py
bipartitepandas/bipartitelong.py
bipartitepandas/bipartitelongbase.py
bipartitepandas/bipartitelongcollapsed.py
bipartitepandas/simbipartite.py
bipartitepandas/util.py
bipartitepandas/grouping/__init__.py
bipartitepandas/grouping/grouping.py
bipartitepandas/measures/__init__.py
bipartitepandas/measures/measures.py
bipartitepandas-1.1.10.dist-info/LICENSE
bipartitepandas-1.1.10.dist-info/METADATA
bipartitepandas-1.1.10.dist-info/WHEEL
bipartitepandas-1.1.10.dist-info/top_level.txt
bipartitepandas-1.1.10.dist-info/RECORD
