Metadata-Version: 2.1
Name: bipartitepandas
Version: 1.1.10
Summary: Python tools for bipartite labor data
Home-page: https://github.com/tlamadon/bipartitepandas/
Author: Thibaut Lamadon
Author-email: thibaut.lamadon@gmail.com
Project-URL: Documentation, https://tlamadon.github.io/bipartitepandas/
Project-URL: GitHub, https://github.com/tlamadon/bipartitepandas/
Classifier: Programming Language :: Python :: 3
Classifier: License :: OSI Approved :: MIT License
Classifier: Operating System :: OS Independent
Requires-Python: >=3.6
License-File: LICENSE
Requires-Dist: paramsdict >=0.0.3
Requires-Dist: numpy
Requires-Dist: pandas <=2.0.3
Requires-Dist: scipy
Requires-Dist: scikit-learn
Requires-Dist: statsmodels
Requires-Dist: igraph >=0.10.0
Requires-Dist: tqdm
